pymc3/__init__.py
pymc3/backports.py
pymc3/blocking.py
pymc3/data.py
pymc3/exceptions.py
pymc3/math.py
pymc3/model.py
pymc3/model_graph.py
pymc3/parallel_sampling.py
pymc3/sampling.py
pymc3/theanof.py
pymc3/util.py
pymc3/vartypes.py
pymc3/backends/__init__.py
pymc3/backends/base.py
pymc3/backends/ndarray.py
pymc3/backends/report.py
pymc3/backends/tracetab.py
pymc3/distributions/__init__.py
pymc3/distributions/bart.py
pymc3/distributions/bound.py
pymc3/distributions/continuous.py
pymc3/distributions/discrete.py
pymc3/distributions/dist_math.py
pymc3/distributions/distribution.py
pymc3/distributions/mixture.py
pymc3/distributions/multivariate.py
pymc3/distributions/posterior_predictive.py
pymc3/distributions/shape_utils.py
pymc3/distributions/simulator.py
pymc3/distributions/special.py
pymc3/distributions/timeseries.py
pymc3/distributions/transforms.py
pymc3/distributions/tree.py
pymc3/glm/__init__.py
pymc3/glm/families.py
pymc3/glm/linear.py
pymc3/glm/utils.py
pymc3/gp/__init__.py
pymc3/gp/cov.py
pymc3/gp/gp.py
pymc3/gp/mean.py
pymc3/gp/util.py
pymc3/ode/__init__.py
pymc3/ode/ode.py
pymc3/ode/utils.py
pymc3/plots/__init__.py
pymc3/plots/posteriorplot.py
pymc3/smc/__init__.py
pymc3/smc/sample_smc.py
pymc3/smc/smc.py
pymc3/stats/__init__.py
pymc3/step_methods/__init__.py
pymc3/step_methods/arraystep.py
pymc3/step_methods/compound.py
pymc3/step_methods/elliptical_slice.py
pymc3/step_methods/gibbs.py
pymc3/step_methods/metropolis.py
pymc3/step_methods/mlda.py
pymc3/step_methods/pgbart.py
pymc3/step_methods/sgmcmc.py
pymc3/step_methods/slicer.py
pymc3/step_methods/step_sizes.py
pymc3/step_methods/hmc/__init__.py
pymc3/step_methods/hmc/base_hmc.py
pymc3/step_methods/hmc/hmc.py
pymc3/step_methods/hmc/integration.py
pymc3/step_methods/hmc/nuts.py
pymc3/step_methods/hmc/quadpotential.py
pymc3/tests/__init__.py
pymc3/tests/backend_fixtures.py
pymc3/tests/checks.py
pymc3/tests/conftest.py
pymc3/tests/helpers.py
pymc3/tests/models.py
pymc3/tests/sampler_fixtures.py
pymc3-3.11.6.dist-info/LICENSE
pymc3-3.11.6.dist-info/METADATA
pymc3-3.11.6.dist-info/WHEEL
pymc3-3.11.6.dist-info/top_level.txt
pymc3-3.11.6.dist-info/RECORD
