Metadata-Version: 2.1
Name: pymc3
Version: 3.11.6
Summary: Probabilistic Programming in Python: Bayesian Modeling and Probabilistic Machine Learning with Theano
Home-page: http://github.com/pymc-devs/pymc3
Maintainer: PyMC Developers
Maintainer-email: pymc.devs@gmail.com
License: Apache License, Version 2.0
Platform: UNKNOWN
Classifier: Development Status :: 5 - Production/Stable
Classifier: Programming Language :: Python
Classifier: Programming Language :: Python :: 3
Classifier: Programming Language :: Python :: 3.7
Classifier: Programming Language :: Python :: 3.8
Classifier: Programming Language :: Python :: 3.9
Classifier: License :: OSI Approved :: Apache Software License
Classifier: Intended Audience :: Science/Research
Classifier: Topic :: Scientific/Engineering
Classifier: Topic :: Scientific/Engineering :: Mathematics
Classifier: Operating System :: OS Independent
Requires-Python: >=3.7
